[1,["65lkAecaFHMJX8lAZNoNph@6c48a"],0,[["sp.SkeletonData",["_name","_atlasText","textureNames","_skeletonJson","textures"],-1,3]],[[0,0,1,2,3,4,5]],[[0,"man114","all.png\nsize: 1953,1095\nformat: RGBA8888\nfilter: Linear,Linear\nrepeat: none\nman114_body\n  rotate: true\n  xy: 242, 415\n  size: 36, 66\n  orig: 38, 68\n  offset: 1, 1\n  index: -1\nman114_hand_l\n  rotate: true\n  xy: 1010, 266\n  size: 14, 57\n  orig: 16, 59\n  offset: 1, 1\n  index: -1\nman114_hand_r\n  rotate: true\n  xy: 1401, 925\n  size: 18, 56\n  orig: 20, 58\n  offset: 1, 1\n  index: -1\nman114_hand_r2\n  rotate: false\n  xy: 468, 274\n  size: 28, 26\n  orig: 30, 28\n  offset: 1, 1\n  index: -1\nman114_head\n  rotate: true\n  xy: 1010, 977\n  size: 57, 42\n  orig: 59, 44\n  offset: 1, 1\n  index: -1\nman114_head_h\n  rotate: true\n  xy: 1131, 978\n  size: 57, 42\n  orig: 59, 44\n  offset: 1, 1\n  index: -1\nman114_leg_l\n  rotate: false\n  xy: 1114, 900\n  size: 23, 76\n  orig: 25, 78\n  offset: 1, 1\n  index: -1\nman114_leg_r\n  rotate: true\n  xy: 535, 408\n  size: 22, 75\n  orig: 24, 77\n  offset: 1, 1\n  index: -1\n",["all.png"],{"skeleton":{"hash":"Fu9sDvo8zDty23B9AFy85M9StrA","spine":"3.8.99","x":-35.76,"y":-1,"width":69.26,"height":158,"images":"../../man114/image/","audio":""},"bones":[{"name":"man114"},{"name":"man114_root","parent":"man114"},{"name":"man114_body","parent":"man114_root","length":29.98,"rotation":82.53,"x":-3.89,"y":70.91},{"name":"man114_head","parent":"man114_body","length":14.93,"rotation":51.91,"x":51.99,"y":0.82},{"name":"man114_hand_l","parent":"man114_body","length":30.82,"rotation":-168.72,"x":40.36,"y":-14.56},{"name":"man114_hand_r","parent":"man114_body","length":25.57,"rotation":175.43,"x":36.17,"y":11.15},{"name":"man114_leg_l","parent":"man114_root","length":23.89,"rotation":-80.62,"x":5.13,"y":66.4},{"name":"man114_leg_r","parent":"man114_root","length":22.64,"rotation":-84.81,"x":-12.91,"y":67.84}],"slots":[{"name":"man114_hand_r2","bone":"man114_hand_r","attachment":"man114_hand_r2"},{"name":"man114_hand_r","bone":"man114_hand_r","attachment":"man114_hand_r"},{"name":"man114_leg_r","bone":"man114_leg_r","attachment":"man114_leg_r"},{"name":"man114_leg_l","bone":"man114_leg_l","attachment":"man114_leg_l"},{"name":"man114_body","bone":"man114_body","attachment":"man114_body"},{"name":"man114_hand_l","bone":"man114_hand_l","attachment":"man114_hand_l"},{"name":"man114_head_h","bone":"man114_head","attachment":"man114_head_h"},{"name":"man114_head","bone":"man114_head","attachment":"man114_head"}],"skins":[{"name":"default","attachments":{"man114_body":{"man114_body":{"x":24.33,"y":-0.23,"rotation":-82.53,"width":38,"height":68}},"man114_hand_l":{"man114_hand_l":{"x":27.56,"y":-0.62,"rotation":86.19,"width":16,"height":59}},"man114_hand_r":{"man114_hand_r":{"x":27.51,"y":1.52,"rotation":102.03,"width":20,"height":58}},"man114_hand_r2":{"man114_hand_r2":{"x":13.64,"y":-7.84,"rotation":102.03,"width":30,"height":28}},"man114_head":{"man114_head":{"x":7.51,"y":-10.09,"rotation":-134.44,"width":59,"height":44}},"man114_head_h":{"man114_head_h":{"x":7.51,"y":-10.09,"rotation":-134.44,"width":59,"height":44}},"man114_leg_l":{"man114_leg_l":{"x":28.49,"y":-1.79,"rotation":80.62,"width":25,"height":78}},"man114_leg_r":{"man114_leg_r":{"x":28.17,"y":-3.15,"rotation":84.81,"width":24,"height":77}}}}],"animations":{"idle":{"slots":{"man114_hand_r2":{"color":[{"color":"ffffff00"}]},"man114_head_h":{"color":[{"color":"ffffff00"}]}},"bones":{"man114_body":{"rotate":[{"angle":-0.2,"curve":0.371,"c2":0.62,"c3":0.71},{"time":0.1667,"curve":0.25,"c3":0.75},{"time":1.1667,"angle":-2.07,"curve":0.243,"c3":0.689,"c4":0.75},{"time":2,"angle":-0.2}],"translate":[{"curve":0.25,"c3":0.75},{"time":1,"y":-1.5,"curve":0.25,"c3":0.75},{"time":2}]},"man114_hand_l":{"rotate":[{"angle":3.96,"curve":0.372,"c2":0.48,"c3":0.752},{"time":0.5333,"curve":0.25,"c3":0.75},{"time":1.5333,"angle":7.28,"curve":0.252,"c3":0.622,"c4":0.48},{"time":2,"angle":3.96}]},"man114_hand_r":{"rotate":[{"angle":-3.32,"curve":0.372,"c2":0.48,"c3":0.752},{"time":0.5333,"curve":0.25,"c3":0.75},{"time":1.5333,"angle":-6.11,"curve":0.252,"c3":0.622,"c4":0.48},{"time":2,"angle":-3.32}]},"man114_head":{"rotate":[{"angle":1.89,"curve":0.382,"c2":0.57,"c3":0.735},{"time":0.3333,"curve":0.25,"c3":0.75},{"time":1.3333,"angle":6.68,"curve":0.243,"c3":0.649,"c4":0.6},{"time":2,"angle":1.89}]}}},"idle2":{"slots":{"man114_hand_r":{"color":[{"color":"ffffff00"}]},"man114_head":{"color":[{"color":"ffffff00"}]}},"bones":{"man114_body":{"rotate":[{"angle":-0.2,"curve":0.371,"c2":0.62,"c3":0.71},{"time":0.1667,"curve":0.25,"c3":0.75},{"time":1.1667,"angle":-2.07,"curve":0.243,"c3":0.689,"c4":0.75},{"time":2,"angle":-0.2}],"translate":[{"curve":0.25,"c3":0.75},{"time":1,"y":-1.5,"curve":0.25,"c3":0.75},{"time":2}]},"man114_hand_l":{"rotate":[{"angle":3.96,"curve":0.372,"c2":0.48,"c3":0.752},{"time":0.5333,"curve":0.25,"c3":0.75},{"time":1.5333,"angle":7.28,"curve":0.252,"c3":0.622,"c4":0.48},{"time":2,"angle":3.96}]},"man114_hand_r":{"rotate":[{"angle":-12.13,"curve":0.372,"c2":0.62,"c3":0.711},{"time":0.2,"angle":-15.51,"curve":0.25,"c3":0.75},{"time":1.0333,"angle":18.23,"curve":0.243,"c3":0.688,"c4":0.74},{"time":2,"angle":-12.13}],"translate":[{"x":0.01,"y":-0.01,"curve":0.25,"c3":0.75},{"time":0.1,"curve":0.25,"c3":0.75},{"time":0.9333,"x":0.19,"y":-0.37,"curve":0.25,"c3":0.75},{"time":2,"x":0.01,"y":-0.01}]},"man114_head":{"rotate":[{"angle":1.89,"curve":0.382,"c2":0.57,"c3":0.735},{"time":0.3333,"curve":0.25,"c3":0.75},{"time":1.3333,"angle":6.68,"curve":0.243,"c3":0.649,"c4":0.6},{"time":2,"angle":1.89}]}}},"walk":{"slots":{"man114_hand_r2":{"color":[{"color":"ffffff00"}]},"man114_head_h":{"color":[{"color":"ffffff00"}]}},"bones":{"man114_body":{"rotate":[{"angle":1.11,"curve":0.364,"c2":0.64,"c3":0.701},{"time":0.0667,"angle":1.43,"curve":0.25,"c3":0.75},{"time":0.6,"angle":-3.7,"curve":0.244,"c3":0.702,"c4":0.8},{"time":1.0667,"angle":1.11}],"translate":[{"curve":0.25,"c3":0.75},{"time":0.2667,"y":1.46,"curve":0.25,"c3":0.75},{"time":0.5333,"curve":0.25,"c3":0.75},{"time":0.8,"y":1.46,"curve":0.25,"c3":0.75},{"time":1.0667}]},"man114_leg_r":{"rotate":[{"angle":-17.3,"curve":0.25,"c3":0.75},{"time":0.5333,"angle":10.2,"curve":0.25,"c3":0.75},{"time":1.0667,"angle":-17.3}],"translate":[{"time":0.5333,"curve":0.25,"c3":0.75},{"time":0.8,"y":6.01,"curve":0.25,"c3":0.75},{"time":1.0667}]},"man114_leg_l":{"rotate":[{"angle":7.65,"curve":0.25,"c3":0.75},{"time":0.5333,"angle":-19.61,"curve":0.25,"c3":0.75},{"time":1.0667,"angle":7.65}],"translate":[{"curve":0.25,"c3":0.75},{"time":0.2667,"y":5.28,"curve":0.25,"c3":0.75},{"time":0.5333}]},"man114_hand_r":{"rotate":[{"angle":17.07,"curve":0.25,"c3":0.75},{"time":0.5333,"angle":-6.76,"curve":0.25,"c3":0.75},{"time":1.0667,"angle":17.07}]},"man114_hand_l":{"rotate":[{"angle":-35.3,"curve":0.25,"c3":0.75},{"time":0.5333,"angle":16.99,"curve":0.25,"c3":0.75},{"time":1.0667,"angle":-35.3}]},"man114_head":{"rotate":[{"angle":1.45,"curve":0.379,"c2":0.6,"c3":0.724},{"time":0.1333,"curve":0.25,"c3":0.75},{"time":0.6667,"angle":7.84,"curve":0.242,"c3":0.667,"c4":0.67},{"time":1.0667,"angle":1.45}]}}}}},[0]]],0,0,[0],[-1],[0]]
