[1,["65lkAecaFHMJX8lAZNoNph@6c48a"],0,[["sp.SkeletonData",["_name","_atlasText","textureNames","_skeletonJson","textures"],-1,3]],[[0,0,1,2,3,4,5]],[[0,"man112","all.png\nsize: 1953,1095\nformat: RGBA8888\nfilter: Linear,Linear\nrepeat: none\nman112_body\n  rotate: true\n  xy: 366, 869\n  size: 50, 81\n  orig: 52, 83\n  offset: 1, 1\n  index: -1\nman112_hand_l\n  rotate: true\n  xy: 534, 154\n  size: 18, 47\n  orig: 20, 49\n  offset: 1, 1\n  index: -1\nman112_hand_r\n  rotate: false\n  xy: 1505, 446\n  size: 18, 49\n  orig: 20, 51\n  offset: 1, 1\n  index: -1\nman112_hand_r2\n  rotate: false\n  xy: 1675, 420\n  size: 28, 28\n  orig: 30, 30\n  offset: 1, 1\n  index: -1\nman112_head\n  rotate: false\n  xy: 1003, 850\n  size: 51, 43\n  orig: 53, 45\n  offset: 1, 1\n  index: -1\nman112_head_h\n  rotate: false\n  xy: 901, 330\n  size: 51, 43\n  orig: 53, 45\n  offset: 1, 1\n  index: -1\nman112_leg_l\n  rotate: false\n  xy: 1143, 472\n  size: 17, 59\n  orig: 19, 61\n  offset: 1, 1\n  index: -1\nman112_leg_r\n  rotate: false\n  xy: 472, 216\n  size: 14, 56\n  orig: 16, 58\n  offset: 1, 1\n  index: -1\n",["all.png"],{"skeleton":{"hash":"3b2YC5D0+UeNTHR6n1VqCrQ33xQ","spine":"3.8.99","x":-36.97,"y":-1,"width":64.97,"height":160,"images":"../../man112/image/","audio":""},"bones":[{"name":"man112"},{"name":"man112_root","parent":"man112"},{"name":"man112_body","parent":"man112_root","length":26.88,"rotation":82.3,"x":-4.38,"y":80.65},{"name":"man112_head","parent":"man112_body","length":17.86,"rotation":43.95,"x":40.68,"y":1.86},{"name":"man112_hand_l","parent":"man112_body","length":19.1,"rotation":-165.85,"x":30.16,"y":-9.48},{"name":"man112_hand_r","parent":"man112_body","length":20.58,"rotation":175.67,"x":29.61,"y":10.59},{"name":"man112_leg_l","parent":"man112_root","length":31.33,"rotation":-79.99,"x":0.15,"y":74.78},{"name":"man112_leg_r","parent":"man112_root","length":28.76,"rotation":-86.71,"x":-9.92,"y":73.79}],"slots":[{"name":"man112_hand_r2","bone":"man112_hand_r","attachment":"man112_hand_r2"},{"name":"man112_hand_r","bone":"man112_hand_r","attachment":"man112_hand_r"},{"name":"man112_leg_r","bone":"man112_leg_r","attachment":"man112_leg_r"},{"name":"man112_leg_l","bone":"man112_leg_l","attachment":"man112_leg_l"},{"name":"man112_body","bone":"man112_body","attachment":"man112_body"},{"name":"man112_hand_l","bone":"man112_hand_l","attachment":"man112_hand_l"},{"name":"man112_head_h","bone":"man112_head","attachment":"man112_head_h"},{"name":"man112_head","bone":"man112_head","attachment":"man112_head"}],"skins":[{"name":"default","attachments":{"man112_body":{"man112_body":{"x":3.21,"y":-2.47,"rotation":-82.3,"width":52,"height":83}},"man112_hand_l":{"man112_hand_l":{"x":21.13,"y":2.08,"rotation":83.55,"width":20,"height":49}},"man112_hand_r":{"man112_hand_r":{"x":23.67,"y":-1.18,"rotation":102.03,"width":20,"height":51}},"man112_hand_r2":{"man112_hand_r2":{"x":14.45,"y":-8.23,"rotation":102.03,"width":30,"height":30}},"man112_head":{"man112_head":{"x":10.98,"y":-10.88,"rotation":-126.25,"width":53,"height":45}},"man112_head_h":{"man112_head_h":{"x":10.98,"y":-10.88,"rotation":-126.25,"width":53,"height":45}},"man112_leg_l":{"man112_leg_l":{"x":45.78,"y":-1.12,"rotation":79.99,"width":19,"height":61}},"man112_leg_r":{"man112_leg_r":{"x":45.71,"y":-2.71,"rotation":86.71,"width":16,"height":58}}}}],"animations":{"idle":{"slots":{"man112_hand_r2":{"color":[{"color":"ffffff00"}]},"man112_head_h":{"color":[{"color":"ffffff00"}]}},"bones":{"man112_body":{"rotate":[{"angle":-0.33,"curve":0.371,"c2":0.62,"c3":0.71},{"time":0.1667,"curve":0.25,"c3":0.75},{"time":1.1667,"angle":-3.46,"curve":0.243,"c3":0.689,"c4":0.75},{"time":2,"angle":-0.33}],"translate":[{"curve":0.25,"c3":0.75},{"time":1,"y":-2.09,"curve":0.25,"c3":0.75},{"time":2}]},"man112_head":{"rotate":[{"angle":2.4,"curve":0.382,"c2":0.57,"c3":0.735},{"time":0.3333,"curve":0.25,"c3":0.75},{"time":1.3333,"angle":8.47,"curve":0.243,"c3":0.649,"c4":0.6},{"time":2,"angle":2.4}]},"man112_hand_r":{"rotate":[{"angle":-3.7,"curve":0.375,"c2":0.5,"c3":0.75},{"time":0.5,"curve":0.25,"c3":0.75},{"time":1.5,"angle":-7.4,"curve":0.25,"c3":0.625,"c4":0.5},{"time":2,"angle":-3.7}]},"man112_hand_l":{"rotate":[{"angle":3.73,"curve":0.375,"c2":0.5,"c3":0.75},{"time":0.5,"curve":0.25,"c3":0.75},{"time":1.5,"angle":7.46,"curve":0.25,"c3":0.625,"c4":0.5},{"time":2,"angle":3.73}]}}},"idle2":{"slots":{"man112_hand_r":{"color":[{"color":"ffffff00"}]},"man112_head":{"color":[{"color":"ffffff00"}]}},"bones":{"man112_body":{"rotate":[{"angle":-0.33,"curve":0.371,"c2":0.62,"c3":0.71},{"time":0.1667,"curve":0.25,"c3":0.75},{"time":1.1667,"angle":-3.46,"curve":0.243,"c3":0.689,"c4":0.75},{"time":2,"angle":-0.33}],"translate":[{"curve":0.25,"c3":0.75},{"time":1,"y":-2.09,"curve":0.25,"c3":0.75},{"time":2}]},"man112_head":{"rotate":[{"angle":2.4,"curve":0.382,"c2":0.57,"c3":0.735},{"time":0.3333,"curve":0.25,"c3":0.75},{"time":1.3333,"angle":8.47,"curve":0.243,"c3":0.649,"c4":0.6},{"time":2,"angle":2.4}]},"man112_hand_r":{"rotate":[{"angle":-20.15,"curve":0.348,"c2":0.66,"c3":0.682},{"time":0.2,"angle":-21.82,"curve":0.25,"c3":0.75},{"time":1.0333,"angle":12.98,"curve":0.37,"c2":0.5,"c3":0.713,"c4":0.88},{"time":2,"angle":-20.15}]},"man112_hand_l":{"rotate":[{"angle":3.73,"curve":0.375,"c2":0.5,"c3":0.75},{"time":0.5,"curve":0.25,"c3":0.75},{"time":1.5,"angle":7.46,"curve":0.25,"c3":0.625,"c4":0.5},{"time":2,"angle":3.73}]}}},"walk":{"slots":{"man112_hand_r2":{"color":[{"color":"ffffff00"}]},"man112_head_h":{"color":[{"color":"ffffff00"}]}},"bones":{"man112_body":{"rotate":[{"angle":-0.24,"curve":0.364,"c2":0.64,"c3":0.701},{"time":0.0667,"curve":0.25,"c3":0.75},{"time":0.6,"angle":-3.88,"curve":0.244,"c3":0.702,"c4":0.8},{"time":1.0667,"angle":-0.24}],"translate":[{"curve":0.25,"c3":0.75},{"time":0.2667,"y":2.63,"curve":0.25,"c3":0.75},{"time":0.5333,"curve":0.25,"c3":0.75},{"time":0.8,"y":2.63,"curve":0.25,"c3":0.75},{"time":1.0667}]},"man112_leg_r":{"rotate":[{"angle":-16.93,"curve":0.25,"c3":0.75},{"time":0.5333,"angle":7.63,"curve":0.25,"c3":0.75},{"time":1.0667,"angle":-16.93}],"translate":[{"time":0.5333,"curve":0.25,"c3":0.75},{"time":0.8,"y":5.54,"curve":0.25,"c3":0.75},{"time":1.0667}]},"man112_leg_l":{"rotate":[{"angle":12.07,"curve":0.25,"c3":0.75},{"time":0.5333,"angle":-21.09,"curve":0.25,"c3":0.75},{"time":1.0667,"angle":12.07}],"translate":[{"curve":0.25,"c3":0.75},{"time":0.2667,"y":4.49,"curve":0.25,"c3":0.75},{"time":0.5333}]},"man112_head":{"rotate":[{"angle":1.44,"curve":0.379,"c2":0.6,"c3":0.724},{"time":0.1333,"curve":0.25,"c3":0.75},{"time":0.6667,"angle":7.79,"curve":0.242,"c3":0.667,"c4":0.67},{"time":1.0667,"angle":1.44}]},"man112_hand_l":{"rotate":[{"angle":-39.02,"curve":0.25,"c3":0.75},{"time":0.5333,"angle":17.83,"curve":0.25,"c3":0.75},{"time":1.0667,"angle":-39.02}]},"man112_hand_r":{"rotate":[{"angle":24.46,"curve":0.25,"c3":0.75},{"time":0.5333,"angle":-11.64,"curve":0.25,"c3":0.75},{"time":1.0667,"angle":24.46}]}}}}},[0]]],0,0,[0],[-1],[0]]
